streamlit_copilot_textarea/__init__.py
streamlit_copilot_textarea/frontend/build/asset-manifest.json
streamlit_copilot_textarea/frontend/build/bootstrap.min.css
streamlit_copilot_textarea/frontend/build/index.html
streamlit_copilot_textarea/frontend/build/static/js/main.ab7481c4.js
streamlit_copilot_textarea/frontend/build/static/js/main.ab7481c4.js.LICENSE.txt
streamlit_copilot_textarea/frontend/build/static/js/main.ab7481c4.js.map
streamlit_copilot_textarea-1.0.2.dist-info/LICENSE
streamlit_copilot_textarea-1.0.2.dist-info/METADATA
streamlit_copilot_textarea-1.0.2.dist-info/WHEEL
streamlit_copilot_textarea-1.0.2.dist-info/RECORD
