Metadata-Version: 2.1
Name: streamlit-copilot-textarea
Version: 1.0.2
Summary: a drop-in replacement for the standard streamlit textarea, offering enhanced autocomplete features powered by AI.
License: MIT
Author: Xueyuan Lin
Author-email: linxy59@mail2.sysu.eud.cn
Requires-Python: >=3.8, !=2.7.*, !=3.0.*, !=3.1.*, !=3.2.*, !=3.3.*, !=3.4.*, !=3.5.*, !=3.6.*, !=3.7.*
Classifier: License :: OSI Approved :: MIT License
Classifier: Programming Language :: Python :: 3
Classifier: Programming Language :: Python :: 3.8
Classifier: Programming Language :: Python :: 3.9
Classifier: Programming Language :: Python :: 3.10
Classifier: Programming Language :: Python :: 3.11
Classifier: Programming Language :: Python :: 3.12
Requires-Dist: streamlit (>=0.63)
